strsafe/__init__.py
strsafe/py.typed
strsafe-1.0.0.dist-info/WHEEL
strsafe-1.0.0.dist-info/METADATA
strsafe-1.0.0.dist-info/RECORD
