Metadata-Version: 2.3
Name: strsafe
Version: 1.0.0
Summary: Transliterate Unicode strings to 'safe' ASCII strings.
Author: Andrew LeCody
Author-email: Andrew LeCody <348675+aceat64@users.noreply.github.com>
Requires-Dist: unidecode>=1.4.0
Requires-Python: >=3.10
